kraken_class_entity/__init__.py
kraken_class_entity/entities.py
kraken_class_entity/entity.py
kraken_class_entity-0.0.7.dist-info/LICENSE.txt
kraken_class_entity-0.0.7.dist-info/METADATA
kraken_class_entity-0.0.7.dist-info/WHEEL
kraken_class_entity-0.0.7.dist-info/top_level.txt
kraken_class_entity-0.0.7.dist-info/RECORD
