Metadata-Version: 2.1
Name: kraken-class-entity
Version: 0.0.7
Summary: Kraken Class entity
Home-page: https://github.com/tactik8/kraken_db_api
Author: Tactik8
Author-email: info@tactik8.com
License: MIT
Platform: UNKNOWN
Classifier: License :: OSI Approved :: MIT License
Classifier: Programming Language :: Python :: 3
Classifier: Programming Language :: Python :: 3.8
License-File: LICENSE.txt
Requires-Dist: aiohttp
Requires-Dist: kraken-schema-org
Requires-Dist: kraken-datatype
